glacium/__init__.py
glacium/cli/__init__.py
glacium/cli/job.py
glacium/cli/list.py
glacium/cli/new.py
glacium/cli/projects.py
glacium/cli/remove.py
glacium/cli/run.py
glacium/cli/select.py
glacium/cli/sync.py
glacium/config/__init__.py
glacium/config/defaults/global_default.yaml
glacium/config/FENSAP.DROP3D.files.yaml
glacium/config/FENSAP.DROP3D.par.yaml
glacium/config/FENSAP.FENSAP.files.yaml
glacium/config/FENSAP.FENSAP.par.yaml
glacium/config/FENSAP.ICE3D.custom_remeshing.sh.yaml
glacium/config/FENSAP.ICE3D.files.yaml
glacium/config/FENSAP.ICE3D.meshingSizes.scm.yaml
glacium/config/FENSAP.ICE3D.par.yaml
glacium/config/FENSAP.ICE3D.remeshing.jou.yaml
glacium/config/FENSAP.solvercmd.yaml
glacium/config/global_default.yaml
glacium/config/mapping.yaml
glacium/config/POINTWISE.GCI.glf.yaml
glacium/config/POINTWISE.run_pointwise.sh.yaml
glacium/config/VSZ.profiles.vsz.yaml
glacium/config/XFOIL.boundarylayer.in.yaml
glacium/config/XFOIL.increasepoints.in.yaml
glacium/config/XFOIL.polars.in.yaml
glacium/config/XFOIL.run_xfoil.sh.yaml
glacium/config/XFOIL.suctioncurve.in.yaml
glacium/config/XFOIL.thickenTE.in.yaml
glacium/data/AH63K127.dat
glacium/engines/__init__.py
glacium/engines/base_engine.py
glacium/engines/fensap.py
glacium/engines/fluent2fensap.py
glacium/engines/pointwise.py
glacium/engines/PointwiseJobs.py
glacium/engines/PyEngine.py
glacium/engines/veusz.py
glacium/engines/xfoil_engine.py
glacium/engines/XfoilBase.py
glacium/engines/XfoilConvertJob.py
glacium/engines/XfoilJobs.py
glacium/index.yaml
glacium/managers/__init__.py
glacium/managers/ConfigManager.py
glacium/managers/JobManager.py
glacium/managers/PathManager.py
glacium/managers/ProjectManager.py
glacium/managers/RecipeManager.py
glacium/managers/TemplateManager.py
glacium/models/__init__.py
glacium/models/config.py
glacium/models/job.py
glacium/models/project.py
glacium/profiles/AH63K127.dat
glacium/recipes/__init__.py
glacium/recipes/default_aero.py
glacium/recipes/fensap.py
glacium-1.1.0.dist-info/entry_points.txt
glacium-1.1.0.dist-info/LICENSE
glacium-1.1.0.dist-info/METADATA
glacium-1.1.0.dist-info/WHEEL
glacium-1.1.0.dist-info/RECORD
