Metadata-Version: 2.3
Name: glacium
Version: 1.1.0
Summary: 
License: MIT
Author: pineOapple
Author-email: 44525727+pineOapple@users.noreply.github.com
Requires-Python: >=3.12
Classifier: License :: OSI Approved :: MIT License
Classifier: Programming Language :: Python
Classifier: Programming Language :: Python :: 3
Classifier: Programming Language :: Python :: 3 :: Only
Classifier: Programming Language :: Python :: 3.12
Requires-Dist: click (>=8)
Requires-Dist: coloredlogs (>=15)
Requires-Dist: jinja2 (>=3)
Requires-Dist: pyyaml (>=6)
Requires-Dist: rich (>=13)
Requires-Dist: verboselogs (>=1)
